phm_diagnosis/__init__.py
phm_diagnosis/api/__init__.py
phm_diagnosis/api/api.py
phm_feature/__init__.py
phm_diagnosis-0.0.1.dist-info/LICENSE
phm_diagnosis-0.0.1.dist-info/METADATA
phm_diagnosis-0.0.1.dist-info/WHEEL
phm_diagnosis-0.0.1.dist-info/top_level.txt
phm_diagnosis-0.0.1.dist-info/RECORD
