Metadata-Version: 2.1
Name: phm-diagnosis
Version: 0.0.1
Summary: failure diagnosis
Home-page: https://github.com/three-quark/phm-diagnosis.git
Author: qin_hai_ning
Author-email: 2364839934@qq.com
License: UNKNOWN
Platform: UNKNOWN
Classifier: Programming Language :: Python :: 3
Classifier: License :: OSI Approved :: Apache Software License
Classifier: Operating System :: OS Independent
